cognitolowlevel/__init__.py
cognitolowlevel/apps.py
cognitolowlevel/models.py
cognitolowlevel/urls.py
cognitolowlevel/views.py
cognitolowlevel/handlers/backend.py
django_cognito_lowlevel-0.1.11.dist-info/METADATA
django_cognito_lowlevel-0.1.11.dist-info/WHEEL
django_cognito_lowlevel-0.1.11.dist-info/licenses/LICENSE
django_cognito_lowlevel-0.1.11.dist-info/RECORD
