Metadata-Version: 2.1
Name: django-cognito-lowlevel
Version: 0.1.11
Summary: Django authentication with AWS Cognito for your custom workflow
Project-URL: Homepage, https://github.com/pulsely/django-cognito-lowlevel
Project-URL: Bug Tracker, https://github.com/pulsely/django-cognito-lowlevel/issues
Author-email: Pulsely <python@pulsely.com>
License-File: LICENSE
Keywords: cognito,django
Classifier: Framework :: Django
Classifier: License :: OSI Approved :: GNU General Public License (GPL)
Classifier: Operating System :: OS Independent
Classifier: Programming Language :: Python :: 3
Classifier: Topic :: Internet :: WWW/HTTP
Classifier: Topic :: Internet :: WWW/HTTP :: Dynamic Content
Requires-Python: >=3.8
Requires-Dist: colorama
Requires-Dist: django>=4.0.0
Requires-Dist: python-jose>=3.3.0
Requires-Dist: requests
